python_firestore/__init__.py
python_firestore/python_firestore.py
pythonfirestore-0.0.1.dist-info/LICENCE
pythonfirestore-0.0.1.dist-info/METADATA
pythonfirestore-0.0.1.dist-info/WHEEL
pythonfirestore-0.0.1.dist-info/top_level.txt
pythonfirestore-0.0.1.dist-info/RECORD
