Metadata-Version: 2.1
Name: pythonfirestore
Version: 0.0.1
Summary: Use firestore in python without the need of firebase Admin API
Home-page: https://github.com/coolcrab28/python_firestore
Author: Lakshya Mahajan
Author-email: lakshyamah.jan@gmail.com
License: UNKNOWN
Project-URL: Bug Tracker, https://github.com/coolcrab28/python_firestore/issues
Platform: UNKNOWN
Classifier: Programming Language :: Python :: 3
Classifier: License :: OSI Approved :: MIT License
Classifier: Operating System :: OS Independent
Requires-Python: >=3.6
License-File: LICENCE
